FunctionScaler
