Metadata-Version: 1.0
Name: FunctionScaler
Version: 0.1
Summary: Given a discrete probability density function learn a function that turns samples from the pdf into samples from desired distribution.
Home-page: https://github.com/weissercn/FunctionScaler
Author: Constantin Weisser
Author-email: weissercn@gmail.com
License: MIT
Platform: UNKNOWN
